phuyentoiyeu/__init__.py
phuyentoiyeu/cat.py
phuyentoiyeu/math.py
phuyentoiyeu-0.1.0.dist-info/METADATA
phuyentoiyeu-0.1.0.dist-info/WHEEL
phuyentoiyeu-0.1.0.dist-info/RECORD
