Metadata-Version: 2.3
Name: phuyentoiyeu
Version: 0.1.0
Summary: A package for thanglieuphuyen
Author: Nguyen Gia Bao
Author-email: bao.luu22022004@hcmut.edu.vn
Requires-Python: >=3.12
Classifier: Programming Language :: Python :: 3
Classifier: Programming Language :: Python :: 3.12
Classifier: Programming Language :: Python :: 3.13
Requires-Dist: numpy (>=2.3.2,<3.0.0)
Requires-Dist: python-math (>=0.0.1,<0.0.2)
